CMakeLists.txt
LICENSE
MANIFEST.in
README.md
SymSpellCppPy.cpp
__init__.py
_version.py
library.cpp
library.h
setup.cfg
setup.py
versioneer.py
./tests/CatchMain.cpp
./tests/SymSpellCppPyTest.py
./tests/__init__.py
SymSpellCppPy.egg-info/PKG-INFO
SymSpellCppPy.egg-info/SOURCES.txt
SymSpellCppPy.egg-info/dependency_links.txt
SymSpellCppPy.egg-info/not-zip-safe
SymSpellCppPy.egg-info/top_level.txt
include/BaseDistance.h
include/BaseSimilarity.h
include/DamerauOSA.h
include/Defines.h
include/EditDistance.h
include/Helpers.h
include/Levenshtein.h
include/difflib.h
include/cereal/access.hpp
include/cereal/cereal.hpp
include/cereal/macros.hpp
include/cereal/specialize.hpp
include/cereal/version.hpp
include/cereal/archives/adapters.hpp
include/cereal/archives/binary.hpp
include/cereal/archives/json.hpp
include/cereal/archives/portable_binary.hpp
include/cereal/archives/xml.hpp
include/cereal/details/helpers.hpp
include/cereal/details/polymorphic_impl.hpp
include/cereal/details/polymorphic_impl_fwd.hpp
include/cereal/details/static_object.hpp
include/cereal/details/traits.hpp
include/cereal/details/util.hpp
include/cereal/external/base64.hpp
include/cereal/external/rapidjson/allocators.h
include/cereal/external/rapidjson/cursorstreamwrapper.h
include/cereal/external/rapidjson/document.h
include/cereal/external/rapidjson/encodedstream.h
include/cereal/external/rapidjson/encodings.h
include/cereal/external/rapidjson/filereadstream.h
include/cereal/external/rapidjson/filewritestream.h
include/cereal/external/rapidjson/fwd.h
include/cereal/external/rapidjson/istreamwrapper.h
include/cereal/external/rapidjson/memorybuffer.h
include/cereal/external/rapidjson/memorystream.h
include/cereal/external/rapidjson/ostreamwrapper.h
include/cereal/external/rapidjson/pointer.h
include/cereal/external/rapidjson/prettywriter.h
include/cereal/external/rapidjson/rapidjson.h
include/cereal/external/rapidjson/reader.h
include/cereal/external/rapidjson/schema.h
include/cereal/external/rapidjson/stream.h
include/cereal/external/rapidjson/stringbuffer.h
include/cereal/external/rapidjson/writer.h
include/cereal/external/rapidjson/error/en.h
