Metadata-Version: 2.1
Name: SymSpellCppPy
Version: 0.0.18
Summary: A Fast SymSpell port for python written in C++ using pybind11.
Home-page: https://github.com/viig99/SymSpellCppPy
Author: Arjun Variar & Mohit Tare
Author-email: accio.arjun@gmail.com
Classifier: Intended Audience :: Developers
Classifier: Natural Language :: English
Classifier: Development Status :: 5 - Production/Stable
Classifier: License :: OSI Approved :: MIT License
Classifier: Programming Language :: Python
Classifier: Programming Language :: Python :: 3
Classifier: Programming Language :: Python :: 3.4
Classifier: Programming Language :: Python :: 3.5
Classifier: Programming Language :: Python :: 3.6
Classifier: Programming Language :: Python :: 3.7
Classifier: Programming Language :: Python :: 3.8
Classifier: Programming Language :: Python :: 3.9
Classifier: Programming Language :: Python :: 3.10
Classifier: Programming Language :: Python :: 3.11
Requires-Python: >=3.4
License-File: LICENSE
